{"lib_name":"测试题库","size":50,"signature":"该题库没有任何描述","questions":[{"tem":"以下哪项属于计算机的五大基本组成之一？","type":1,"difficulty":1,"analysis":"计算机五大组成包括控制器、运算器、存储器、输入设备、输出设备。","options":[{"index":1,"value":"传感器"},{"index":2,"value":"控制器"},{"index":3,"value":"天线"},{"index":4,"value":"交换机"}],"answers":"2"},{"tem":"下列哪个 HTTP 状态码表示“未找到资源”？","type":1,"difficulty":1,"analysis":"404 表示客户端请求的资源不存在。","options":[{"index":1,"value":"200"},{"index":2,"value":"301"},{"index":3,"value":"404"},{"index":4,"value":"500"}],"answers":"3"},{"tem":"Java 中用于创建对象的关键字是？","type":1,"difficulty":1,"analysis":"使用 new 来实例化对象。","options":[{"index":1,"value":"class"},{"index":2,"value":"new"},{"index":3,"value":"import"},{"index":4,"value":"extends"}],"answers":"2"},{"tem":"以下哪种数据结构遵循先进先出（FIFO）？","type":1,"difficulty":1,"analysis":"队列特点是先进先出。","options":[{"index":1,"value":"栈"},{"index":2,"value":"队列"},{"index":3,"value":"树"},{"index":4,"value":"图"}],"answers":"2"},{"tem":"CSS 中控制元素文字颜色的属性是？","type":1,"difficulty":1,"analysis":"color 用于设置文字颜色。","options":[{"index":1,"value":"text-color"},{"index":2,"value":"font-style"},{"index":3,"value":"color"},{"index":4,"value":"text"}],"answers":"3"},{"tem":"SQL 中用于删除表中所有数据但不删除表结构的命令是？","type":1,"difficulty":1,"analysis":"TRUNCATE 可以快速清空数据但保留结构。","options":[{"index":1,"value":"DROP"},{"index":2,"value":"REMOVE"},{"index":3,"value":"DELETE"},{"index":4,"value":"TRUNCATE"}],"answers":"4"},{"tem":"下列哪个属于编译型语言？","type":1,"difficulty":1,"analysis":"C 属于典型的编译型语言。","options":[{"index":1,"value":"Python"},{"index":2,"value":"JavaScript"},{"index":3,"value":"Java（字节码）"},{"index":4,"value":"C"}],"answers":"4"},{"tem":"网络中用于唯一标识一台主机的是？","type":1,"difficulty":1,"analysis":"MAC 地址唯一标识设备网络接口。","options":[{"index":1,"value":"MAC 地址"},{"index":2,"value":"网关"},{"index":3,"value":"子网掩码"},{"index":4,"value":"DNS"}],"answers":"1"},{"tem":"Git 中用于查看提交历史的命令是？","type":1,"difficulty":1,"analysis":"git log 用于查看提交历史。","options":[{"index":1,"value":"git push"},{"index":2,"value":"git log"},{"index":3,"value":"git status"},{"index":4,"value":"git reset"}],"answers":"2"},{"tem":"HTML 中插入图片使用的标签是？","type":1,"difficulty":1,"analysis":"<img> 标签用于插入图片。","options":[{"index":1,"value":"<pic>"},{"index":2,"value":"<image>"},{"index":3,"value":"<img>"},{"index":4,"value":"<src>"}],"answers":"3"},{"tem":"以下哪些属于面向对象的三大特性？","type":2,"difficulty":1,"analysis":"递归不是面向对象特性。","options":[{"index":1,"value":"封装"},{"index":2,"value":"继承"},{"index":3,"value":"多态"},{"index":4,"value":"递归"}],"answers":[1,2,3]},{"tem":"下列哪些是常用的 HTTP 请求方法？","type":2,"difficulty":1,"analysis":"这些都是标准 HTTP 方法。","options":[{"index":1,"value":"GET"},{"index":2,"value":"POST"},{"index":3,"value":"PUT"},{"index":4,"value":"PATCH"}],"answers":[1,2,3,4]},{"tem":"以下哪些属于关系数据库？","type":2,"difficulty":1,"analysis":"MongoDB 属于文档型数据库。","options":[{"index":1,"value":"MySQL"},{"index":2,"value":"PostgreSQL"},{"index":3,"value":"MongoDB"},{"index":4,"value":"Oracle"}],"answers":[1,2,4]},{"tem":"以下哪些是 JavaScript 中的原始类型？","type":2,"difficulty":1,"analysis":"object 不是原始类型。","options":[{"index":1,"value":"string"},{"index":2,"value":"number"},{"index":3,"value":"boolean"},{"index":4,"value":"object"}],"answers":[1,2,3]},{"tem":"下列哪些协议属于应用层协议？","type":2,"difficulty":1,"analysis":"TCP 属于传输层协议。","options":[{"index":1,"value":"HTTP"},{"index":2,"value":"FTP"},{"index":3,"value":"TCP"},{"index":4,"value":"SMTP"}],"answers":[1,2,4]},{"tem":"以下哪些结构属于树形结构？","type":2,"difficulty":1,"analysis":"队列不属于树结构。","options":[{"index":1,"value":"文件系统目录"},{"index":2,"value":"HTML DOM"},{"index":3,"value":"二叉树"},{"index":4,"value":"队列"}],"answers":[1,2,3]},{"tem":"下列哪些属于 CSS 布局方式？","type":2,"difficulty":1,"analysis":"table 是表格元素，不是布局方式。","options":[{"index":1,"value":"flex"},{"index":2,"value":"grid"},{"index":3,"value":"table"},{"index":4,"value":"float"}],"answers":[1,2,4]},{"tem":"下列哪些属于前端构建工具？","type":2,"difficulty":1,"analysis":"Maven 是 Java 的构建工具。","options":[{"index":1,"value":"Webpack"},{"index":2,"value":"Rollup"},{"index":3,"value":"Vite"},{"index":4,"value":"Maven"}],"answers":[1,2,3]},{"tem":"以下哪些属于操作系统功能？","type":2,"difficulty":1,"analysis":"路由属于网络设备功能。","options":[{"index":1,"value":"进程管理"},{"index":2,"value":"内存管理"},{"index":3,"value":"文件管理"},{"index":4,"value":"网络传输层的路由"}],"answers":[1,2,3]},{"tem":"关于 Git 分支描述正确的是：","type":2,"difficulty":1,"analysis":"Git 分支轻量，不耗资源。","options":[{"index":1,"value":"可以并行开发"},{"index":2,"value":"创建分支很耗资源"},{"index":3,"value":"可以合并分支"},{"index":4,"value":"每个分支互不影响"}],"answers":[1,3,4]},{"tem":"JavaScript 是单线程语言。","type":3,"difficulty":1,"analysis":"JS 的运行主线程是单线程。","answers":1},{"tem":"计算机中的 RAM 属于永久存储。","type":3,"difficulty":1,"analysis":"RAM 属于易失性存储。","answers":0},{"tem":"SQL 中的 WHERE 用于筛选查询数据。","type":3,"difficulty":1,"analysis":"WHERE 用于过滤条件。","answers":1},{"tem":"CSS 中 margin 会影响元素的实际大小。","type":3,"difficulty":1,"analysis":"margin 不计入元素盒模型宽高。","answers":0},{"tem":"前端不能直接操作数据库。","type":3,"difficulty":1,"analysis":"前端访问数据库需经过后端。","answers":1},{"tem":"HTTP 只能使用 80 端口。","type":3,"difficulty":1,"analysis":"HTTP 默认 80，但可自定义。","answers":0},{"tem":"JSON 数据格式仅支持字符串键。","type":3,"difficulty":1,"analysis":"JSON key 必须是字符串。","answers":1},{"tem":"Git 提交之前必须先创建仓库。","type":3,"difficulty":1,"analysis":"必须 git init 创建仓库。","answers":1},{"tem":"Vue 是一个基于 MVC 模式的框架。","type":3,"difficulty":1,"analysis":"Vue 更接近 MVVM。","answers":0},{"tem":"HTTPS 相比 HTTP 多了 SSL/TLS 加密层。","type":3,"difficulty":1,"analysis":"HTTPS 在 HTTP 之上加入加密层。","answers":1},{"tem":"计算机中 CPU 的两大核心部件是 {} 和 {}。","type":4,"difficulty":1,"analysis":"CPU 由控制器与运算器组成。","answers":[{"index":1,"value":"控制器"},{"index":1,"value":"运算器"}]},{"tem":"Web 开发中，CSS 的层叠优先级遵循 {} > {} > {}。","type":4,"difficulty":1,"analysis":"优先级从高到低依次如上。","answers":[{"index":1,"value":"!important"},{"index":1,"value":"内联样式"},{"index":1,"value":"外部/内部样式"}]},{"tem":"Java 中字符串使用的类名是 {}。","type":4,"difficulty":1,"analysis":"Java 字符串属于 String 类。","answers":[{"index":1,"value":"String"}]},{"tem":"MySQL 中查询数据使用的关键字是 {}。","type":4,"difficulty":1,"analysis":"SELECT 用于查询数据。","answers":[{"index":1,"value":"SELECT"}]},{"tem":"HTML5 提供的用于绘图的标签是 {}。","type":4,"difficulty":1,"analysis":"canvas 用于绘制图形。","answers":[{"index":1,"value":"canvas"}]},{"tem":"URL 由三部分构成：协议、域名和 {}。","type":4,"difficulty":1,"analysis":"路径用于标识服务器资源位置。","answers":[{"index":1,"value":"路径"}]},{"tem":"一条 CSS 规则由选择器和 {} 组成。","type":4,"difficulty":1,"analysis":"声明块包含属性和值。","answers":[{"index":1,"value":"声明块"}]},{"tem":"Git 中用于创建新分支的命令是 git {}。","type":4,"difficulty":1,"analysis":"git branch 用于创建分支。","answers":[{"index":1,"value":"branch"}]},{"tem":"JavaScript 中用来定义变量的三个关键字是 {}、{}、{}。","type":4,"difficulty":1,"analysis":"三者均可声明变量。","answers":[{"index":1,"value":"var"},{"index":1,"value":"let"},{"index":1,"value":"const"}]},{"tem":"HTTP 的无状态特性通常通过 {} 技术来维持用户会话。","type":4,"difficulty":1,"analysis":"Cookie 可保持会话状态。","answers":[{"index":1,"value":"Cookie"}]},{"tem":"简述 HTML 的作用。","type":5,"difficulty":1,"analysis":"HTML 是网页的结构化语言。","answers":"用于描述网页结构和内容。"},{"tem":"解释什么是跨域。","type":5,"difficulty":1,"analysis":"跨域是浏览器同源策略导致的问题。","answers":"浏览器出于安全限制，禁止不同源之间相互访问资源的行为。"},{"tem":"简述 Git 的用途。","type":5,"difficulty":1,"analysis":"Git 是分布式版本控制系统。","answers":"用于代码版本控制，实现协作开发与历史追踪。"},{"tem":"说明什么是 RESTful API。","type":5,"difficulty":1,"analysis":"REST 强调资源与无状态通信。","answers":"一种基于资源、使用标准 HTTP 方法进行操作的 API 风格。"},{"tem":"解释变量的作用域是什么。","type":5,"difficulty":1,"analysis":"不同语言支持不同的作用域类型。","answers":"指变量在代码中可被访问的范围。"},{"tem":"简述 TCP 和 UDP 的区别。","type":5,"difficulty":1,"analysis":"两者属于传输层协议。","answers":"TCP 面向连接、可靠；UDP 无连接、不保证可靠性但效率高。"},{"tem":"什么是前端组件化？","type":5,"difficulty":1,"analysis":"组件化提升复用和维护性。","answers":"将页面功能拆分为可复用、可组合的独立模块。"},{"tem":"描述 SQL 中主键的作用。","type":5,"difficulty":1,"analysis":"主键用于唯一性约束。","answers":"唯一标识表中一条记录，不允许重复和 NULL。"},{"tem":"解释什么是 DOM。","type":5,"difficulty":1,"analysis":"DOM 提供节点操作接口。","answers":"浏览器解析 HTML 后形成的树状文档对象模型。"},{"tem":"什么是缓存？","type":5,"difficulty":1,"analysis":"缓存提升系统性能。","answers":"将数据暂时存放在快速存储介质中，以加速访问。"}],"errors":[],"errorCount":0,"successCount":50}